imucal/__init__.py
imucal/calibration_gui.py
imucal/calibration_info.py
imucal/ferraris_calibration.py
imucal/ferraris_calibration_info.py
imucal/legacy.py
imucal/management.py
imucal-2.6.0.dist-info/LICENSE
imucal-2.6.0.dist-info/METADATA
imucal-2.6.0.dist-info/WHEEL
imucal-2.6.0.dist-info/RECORD
