Metadata-Version: 2.1
Name: imucal
Version: 2.6.0
Summary: A Python library to calibrate 6 DOF IMUs
Home-page: https://github.com/mad-lab-fau/imucal
License: MIT
Keywords: sensors,scientific,IMU,accelerometer
Author: Arne Küderle
Author-email: arne.kuederle@fau.de
Requires-Python: >=3.9,<3.14
Classifier: Intended Audience :: Science/Research
Classifier: License :: OSI Approved :: MIT License
Classifier: Programming Language :: Python :: 3
Classifier: Programming Language :: Python :: 3.9
Classifier: Programming Language :: Python :: 3.10
Classifier: Programming Language :: Python :: 3.11
Classifier: Programming Language :: Python :: 3.12
Classifier: Programming Language :: Python :: 3.13
Classifier: Topic :: Scientific/Engineering
Classifier: Topic :: Scientific/Engineering :: Physics
Provides-Extra: calplot
Provides-Extra: h5py
Requires-Dist: h5py (>=3) ; extra == "h5py"
Requires-Dist: matplotlib (>=3.9.2) ; extra == "calplot"
Requires-Dist: numpy (>=1.25.2)
Requires-Dist: packaging (>=21.3)
Requires-Dist: pandas (>=2.0.0)
Project-URL: Documentation, https://imcucal.readthedocs.io/en/latest/
Project-URL: Repository, https://github.com/mad-lab-fau/imucal
